[
{"Date":"1999-08-21","Team 1":"Ath Bilbao","Team 2":"Betis","FT":"1-0","HT":"0-0"},
{"Date":"1999-08-21","Team 1":"Mallorca","Team 2":"Real Madrid","FT":"1-2","HT":"0-0"},
{"Date":"1999-08-21","Team 1":"Valencia","Team 2":"Santander","FT":"1-2","HT":"0-1"},
{"Date":"1999-08-22","Team 1":"Ath Madrid","Team 2":"Vallecano","FT":"0-2","HT":"0-1"},
{"Date":"1999-08-22","Team 1":"Barcelona","Team 2":"Zaragoza","FT":"2-0","HT":"0-0"},
{"Date":"1999-08-22","Team 1":"La Coruna","Team 2":"Alaves","FT":"4-1","HT":"3-1"},
{"Date":"1999-08-22","Team 1":"Malaga","Team 2":"Espanol","FT":"1-0","HT":"0-0"},
{"Date":"1999-08-22","Team 1":"Numancia","Team 2":"Valladolid","FT":"1-0","HT":"1-0"},
{"Date":"1999-08-22","Team 1":"Oviedo","Team 2":"Celta","FT":"1-0","HT":"0-0"},
{"Date":"1999-08-22","Team 1":"Sevilla","Team 2":"Sociedad","FT":"2-2","HT":"2-1"},
{"Date":"1999-08-28","Team 1":"Sociedad","Team 2":"Ath Madrid","FT":"4-1","HT":"0-1"},
{"Date":"1999-08-29","Team 1":"Alaves","Team 2":"Malaga","FT":"2-1","HT":"0-1"},
{"Date":"1999-08-29","Team 1":"Betis","Team 2":"La Coruna","FT":"0-0","HT":"0-0"},
{"Date":"1999-08-29","Team 1":"Celta","Team 2":"Sevilla","FT":"2-1","HT":"1-0"},
{"Date":"1999-08-29","Team 1":"Espanol","Team 2":"Valencia","FT":"3-2","HT":"2-0"},
{"Date":"1999-08-29","Team 1":"Real Madrid","Team 2":"Numancia","FT":"4-1","HT":"0-0"},
{"Date":"1999-08-29","Team 1":"Santander","Team 2":"Barcelona","FT":"1-2","HT":"0-2"},
{"Date":"1999-08-29","Team 1":"Valladolid","Team 2":"Ath Bilbao","FT":"1-0","HT":"1-0"},
{"Date":"1999-08-29","Team 1":"Vallecano","Team 2":"Mallorca","FT":"2-1","HT":"0-1"},
{"Date":"1999-08-29","Team 1":"Zaragoza","Team 2":"Oviedo","FT":"4-0","HT":"2-0"},
{"Date":"1999-09-11","Team 1":"Barcelona","Team 2":"Espanol","FT":"3-0","HT":"0-0"},
{"Date":"1999-09-11","Team 1":"La Coruna","Team 2":"Valladolid","FT":"2-0","HT":"2-0"},
{"Date":"1999-09-11","Team 1":"Valencia","Team 2":"Alaves","FT":"0-2","HT":"0-0"},
{"Date":"1999-09-12","Team 1":"Ath Bilbao","Team 2":"Real Madrid","FT":"2-2","HT":"2-1"},
{"Date":"1999-09-12","Team 1":"Ath Madrid","Team 2":"Celta","FT":"1-2","HT":"1-1"},
{"Date":"1999-09-12","Team 1":"Malaga","Team 2":"Betis","FT":"3-0","HT":"1-0"},
{"Date":"1999-09-12","Team 1":"Mallorca","Team 2":"Numancia","FT":"3-0","HT":"3-0"},
{"Date":"1999-09-12","Team 1":"Oviedo","Team 2":"Santander","FT":"1-2","HT":"0-2"},
{"Date":"1999-09-12","Team 1":"Sevilla","Team 2":"Zaragoza","FT":"0-0","HT":"0-0"},
{"Date":"1999-09-12","Team 1":"Vallecano","Team 2":"Sociedad","FT":"2-1","HT":"1-0"},
{"Date":"1999-09-18","Team 1":"Alaves","Team 2":"Barcelona","FT":"2-1","HT":"1-1"},
{"Date":"1999-09-18","Team 1":"Betis","Team 2":"Valencia","FT":"1-0","HT":"1-0"},
{"Date":"1999-09-18","Team 1":"Espanol","Team 2":"Oviedo","FT":"2-1","HT":"0-1"},
{"Date":"1999-09-18","Team 1":"Real Madrid","Team 2":"La Coruna","FT":"1-1","HT":"0-0"},
{"Date":"1999-09-18","Team 1":"Valladolid","Team 2":"Malaga","FT":"4-2","HT":"1-1"},
{"Date":"1999-09-19","Team 1":"Celta","Team 2":"Vallecano","FT":"0-1","HT":"0-0"},
{"Date":"1999-09-19","Team 1":"Numancia","Team 2":"Ath Bilbao","FT":"1-1","HT":"1-1"},
{"Date":"1999-09-19","Team 1":"Santander","Team 2":"Sevilla","FT":"2-2","HT":"1-2"},
{"Date":"1999-09-19","Team 1":"Sociedad","Team 2":"Mallorca","FT":"2-1","HT":"1-0"},
{"Date":"1999-09-19","Team 1":"Zaragoza","Team 2":"Ath Madrid","FT":"1-1","HT":"1-1"},
{"Date":"1999-09-25","Team 1":"Barcelona","Team 2":"Betis","FT":"4-1","HT":"2-1"},
{"Date":"1999-09-25","Team 1":"Malaga","Team 2":"Real Madrid","FT":"1-1","HT":"0-1"},
{"Date":"1999-09-25","Team 1":"Sociedad","Team 2":"Celta","FT":"0-2","HT":"0-0"},
{"Date":"1999-09-25","Team 1":"Valencia","Team 2":"Valladolid","FT":"0-0","HT":"0-0"},
{"Date":"1999-09-26","Team 1":"Ath Madrid","Team 2":"Santander","FT":"2-0","HT":"0-0"},
{"Date":"1999-09-26","Team 1":"La Coruna","Team 2":"Numancia","FT":"0-2","HT":"0-1"},
{"Date":"1999-09-26","Team 1":"Mallorca","Team 2":"Ath Bilbao","FT":"2-1","HT":"1-0"},
{"Date":"1999-09-26","Team 1":"Oviedo","Team 2":"Alaves","FT":"1-0","HT":"1-0"},
{"Date":"1999-09-26","Team 1":"Sevilla","Team 2":"Espanol","FT":"1-2","HT":"1-1"},
{"Date":"1999-09-26","Team 1":"Vallecano","Team 2":"Zaragoza","FT":"0-1","HT":"0-0"},
{"Date":"1999-10-02","Team 1":"Numancia","Team 2":"Malaga","FT":"1-1","HT":"0-1"},
{"Date":"1999-10-02","Team 1":"Valladolid","Team 2":"Barcelona","FT":"0-2","HT":"0-1"},
{"Date":"1999-10-03","Team 1":"Alaves","Team 2":"Sevilla","FT":"0-0","HT":"0-0"},
{"Date":"1999-10-03","Team 1":"Ath Bilbao","Team 2":"La Coruna","FT":"2-3","HT":"0-1"},
{"Date":"1999-10-03","Team 1":"Betis","Team 2":"Oviedo","FT":"1-0","HT":"1-0"},
{"Date":"1999-10-03","Team 1":"Celta","Team 2":"Mallorca","FT":"1-0","HT":"0-0"},
{"Date":"1999-10-03","Team 1":"Espanol","Team 2":"Ath Madrid","FT":"3-1","HT":"1-1"},
{"Date":"1999-10-03","Team 1":"Real Madrid","Team 2":"Valencia","FT":"2-3","HT":"0-3"},
{"Date":"1999-10-03","Team 1":"Santander","Team 2":"Vallecano","FT":"1-1","HT":"0-0"},
{"Date":"1999-10-03","Team 1":"Zaragoza","Team 2":"Sociedad","FT":"2-0","HT":"0-0"},
{"Date":"1999-10-11","Team 1":"Ath Madrid","Team 2":"Alaves","FT":"1-0","HT":"0-0"},
{"Date":"1999-10-12","Team 1":"Malaga","Team 2":"Ath Bilbao","FT":"3-4","HT":"1-1"},
{"Date":"1999-10-12","Team 1":"Mallorca","Team 2":"La Coruna","FT":"2-2","HT":"0-0"},
{"Date":"1999-10-12","Team 1":"Sevilla","Team 2":"Betis","FT":"3-0","HT":"1-0"},
{"Date":"1999-10-13","Team 1":"Barcelona","Team 2":"Real Madrid","FT":"2-2","HT":"1-1"},
{"Date":"1999-10-13","Team 1":"Celta","Team 2":"Zaragoza","FT":"2-1","HT":"1-1"},
{"Date":"1999-10-13","Team 1":"Oviedo","Team 2":"Valladolid","FT":"1-1","HT":"1-0"},
{"Date":"1999-10-13","Team 1":"Sociedad","Team 2":"Santander","FT":"2-5","HT":"1-0"},
{"Date":"1999-10-13","Team 1":"Valencia","Team 2":"Numancia","FT":"4-0","HT":"1-0"},
{"Date":"1999-10-13","Team 1":"Vallecano","Team 2":"Espanol","FT":"2-1","HT":"0-0"},
{"Date":"1999-10-16","Team 1":"Ath Bilbao","Team 2":"Valencia","FT":"1-0","HT":"1-0"},
{"Date":"1999-10-16","Team 1":"La Coruna","Team 2":"Malaga","FT":"4-1","HT":"1-1"},
{"Date":"1999-10-16","Team 1":"Numancia","Team 2":"Barcelona","FT":"3-3","HT":"0-1"},
{"Date":"1999-10-16","Team 1":"Real Madrid","Team 2":"Oviedo","FT":"2-2","HT":"2-1"},
{"Date":"1999-10-16","Team 1":"Santander","Team 2":"Celta","FT":"3-0","HT":"3-0"},
{"Date":"1999-10-17","Team 1":"Alaves","Team 2":"Vallecano","FT":"0-1","HT":"0-0"},
{"Date":"1999-10-17","Team 1":"Betis","Team 2":"Ath Madrid","FT":"2-1","HT":"1-1"},
{"Date":"1999-10-17","Team 1":"Espanol","Team 2":"Sociedad","FT":"0-0","HT":"0-0"},
{"Date":"1999-10-17","Team 1":"Valladolid","Team 2":"Sevilla","FT":"2-1","HT":"1-1"},
{"Date":"1999-10-17","Team 1":"Zaragoza","Team 2":"Mallorca","FT":"3-0","HT":"0-0"},
{"Date":"1999-10-23","Team 1":"Barcelona","Team 2":"Ath Bilbao","FT":"4-0","HT":"1-0"},
{"Date":"1999-10-23","Team 1":"Sevilla","Team 2":"Real Madrid","FT":"1-1","HT":"1-0"},
{"Date":"1999-10-23","Team 1":"Valencia","Team 2":"La Coruna","FT":"2-0","HT":"1-0"},
{"Date":"1999-10-24","Team 1":"Ath Madrid","Team 2":"Valladolid","FT":"3-1","HT":"1-0"},
{"Date":"1999-10-24","Team 1":"Celta","Team 2":"Espanol","FT":"2-1","HT":"1-1"},
{"Date":"1999-10-24","Team 1":"Mallorca","Team 2":"Malaga","FT":"2-1","HT":"2-0"},
{"Date":"1999-10-24","Team 1":"Oviedo","Team 2":"Numancia","FT":"1-0","HT":"0-0"},
{"Date":"1999-10-24","Team 1":"Sociedad","Team 2":"Alaves","FT":"1-1","HT":"1-1"},
{"Date":"1999-10-24","Team 1":"Vallecano","Team 2":"Betis","FT":"1-3","HT":"0-0"},
{"Date":"1999-10-24","Team 1":"Zaragoza","Team 2":"Santander","FT":"4-1","HT":"1-0"},
{"Date":"1999-10-30","Team 1":"La Coruna","Team 2":"Barcelona","FT":"2-1","HT":"2-0"},
{"Date":"1999-10-30","Team 1":"Malaga","Team 2":"Valencia","FT":"1-1","HT":"1-0"},
{"Date":"1999-10-30","Team 1":"Real Madrid","Team 2":"Ath Madrid","FT":"1-3","HT":"1-3"},
{"Date":"1999-10-31","Team 1":"Alaves","Team 2":"Celta","FT":"1-0","HT":"0-0"},
{"Date":"1999-10-31","Team 1":"Ath Bilbao","Team 2":"Oviedo","FT":"1-1","HT":"1-1"},
{"Date":"1999-10-31","Team 1":"Betis","Team 2":"Sociedad","FT":"1-0","HT":"1-0"},
{"Date":"1999-10-31","Team 1":"Espanol","Team 2":"Zaragoza","FT":"1-1","HT":"0-1"},
{"Date":"1999-10-31","Team 1":"Numancia","Team 2":"Sevilla","FT":"2-0","HT":"1-0"},
{"Date":"1999-10-31","Team 1":"Santander","Team 2":"Mallorca","FT":"1-1","HT":"0-0"},
{"Date":"1999-10-31","Team 1":"Valladolid","Team 2":"Vallecano","FT":"1-2","HT":"0-1"},
{"Date":"1999-11-06","Team 1":"Vallecano","Team 2":"Real Madrid","FT":"2-3","HT":"2-0"},
{"Date":"1999-11-07","Team 1":"Ath Madrid","Team 2":"Numancia","FT":"2-2","HT":"2-0"},
{"Date":"1999-11-07","Team 1":"Barcelona","Team 2":"Malaga","FT":"1-2","HT":"1-2"},
{"Date":"1999-11-07","Team 1":"Celta","Team 2":"Betis","FT":"5-1","HT":"3-1"},
{"Date":"1999-11-07","Team 1":"Mallorca","Team 2":"Valencia","FT":"1-0","HT":"0-0"},
{"Date":"1999-11-07","Team 1":"Oviedo","Team 2":"La Coruna","FT":"0-1","HT":"0-0"},
{"Date":"1999-11-07","Team 1":"Santander","Team 2":"Espanol","FT":"2-2","HT":"1-1"},
{"Date":"1999-11-07","Team 1":"Sevilla","Team 2":"Ath Bilbao","FT":"0-0","HT":"0-0"},
{"Date":"1999-11-07","Team 1":"Sociedad","Team 2":"Valladolid","FT":"3-0","HT":"2-0"},
{"Date":"1999-11-07","Team 1":"Zaragoza","Team 2":"Alaves","FT":"2-1","HT":"1-0"},
{"Date":"1999-11-20","Team 1":"Ath Bilbao","Team 2":"Ath Madrid","FT":"4-2","HT":"2-1"},
{"Date":"1999-11-20","Team 1":"Valencia","Team 2":"Barcelona","FT":"3-1","HT":"2-1"},
{"Date":"1999-11-21","Team 1":"Betis","Team 2":"Zaragoza","FT":"2-0","HT":"1-0"},
{"Date":"1999-11-21","Team 1":"Espanol","Team 2":"Mallorca","FT":"1-2","HT":"0-2"},
{"Date":"1999-11-21","Team 1":"Malaga","Team 2":"Oviedo","FT":"4-0","HT":"2-0"},
{"Date":"1999-11-21","Team 1":"Numancia","Team 2":"Vallecano","FT":"3-1","HT":"0-0"},
{"Date":"1999-11-21","Team 1":"Real Madrid","Team 2":"Sociedad","FT":"1-1","HT":"0-0"},
{"Date":"1999-11-21","Team 1":"Valladolid","Team 2":"Celta","FT":"1-3","HT":"0-1"},
{"Date":"1999-11-22","Team 1":"La Coruna","Team 2":"Sevilla","FT":"5-2","HT":"2-1"},
{"Date":"1999-11-27","Team 1":"Sevilla","Team 2":"Malaga","FT":"0-0","HT":"0-0"},
{"Date":"1999-11-28","Team 1":"Ath Madrid","Team 2":"La Coruna","FT":"1-3","HT":"0-3"},
{"Date":"1999-11-28","Team 1":"Celta","Team 2":"Real Madrid","FT":"1-0","HT":"1-0"},
{"Date":"1999-11-28","Team 1":"Espanol","Team 2":"Alaves","FT":"2-3","HT":"1-2"},
{"Date":"1999-11-28","Team 1":"Mallorca","Team 2":"Barcelona","FT":"3-2","HT":"2-1"},
{"Date":"1999-11-28","Team 1":"Oviedo","Team 2":"Valencia","FT":"0-0","HT":"0-0"},
{"Date":"1999-11-28","Team 1":"Santander","Team 2":"Betis","FT":"1-1","HT":"1-1"},
{"Date":"1999-11-28","Team 1":"Sociedad","Team 2":"Numancia","FT":"2-1","HT":"0-1"},
{"Date":"1999-11-28","Team 1":"Vallecano","Team 2":"Ath Bilbao","FT":"1-2","HT":"0-2"},
{"Date":"1999-11-28","Team 1":"Zaragoza","Team 2":"Valladolid","FT":"1-1","HT":"1-0"},
{"Date":"1999-12-04","Team 1":"Ath Bilbao","Team 2":"Sociedad","FT":"1-1","HT":"1-0"},
{"Date":"1999-12-04","Team 1":"Barcelona","Team 2":"Oviedo","FT":"3-2","HT":"3-0"},
{"Date":"1999-12-04","Team 1":"Real Madrid","Team 2":"Zaragoza","FT":"1-5","HT":"0-3"},
{"Date":"1999-12-04","Team 1":"Valencia","Team 2":"Sevilla","FT":"2-0","HT":"1-0"},
{"Date":"1999-12-05","Team 1":"Alaves","Team 2":"Mallorca","FT":"2-2","HT":"1-0"},
{"Date":"1999-12-05","Team 1":"Betis","Team 2":"Espanol","FT":"2-5","HT":"1-0"},
{"Date":"1999-12-05","Team 1":"La Coruna","Team 2":"Vallecano","FT":"3-2","HT":"3-1"},
{"Date":"1999-12-05","Team 1":"Malaga","Team 2":"Ath Madrid","FT":"2-3","HT":"1-2"},
{"Date":"1999-12-05","Team 1":"Numancia","Team 2":"Celta","FT":"3-1","HT":"1-0"},
{"Date":"1999-12-05","Team 1":"Valladolid","Team 2":"Santander","FT":"1-0","HT":"1-0"},
{"Date":"1999-12-08","Team 1":"Alaves","Team 2":"Santander","FT":"2-1","HT":"1-0"},
{"Date":"1999-12-11","Team 1":"Sevilla","Team 2":"Barcelona","FT":"3-2","HT":"1-1"},
{"Date":"1999-12-12","Team 1":"Alaves","Team 2":"Betis","FT":"2-0","HT":"1-0"},
{"Date":"1999-12-12","Team 1":"Ath Madrid","Team 2":"Valencia","FT":"1-2","HT":"1-1"},
{"Date":"1999-12-12","Team 1":"Celta","Team 2":"Ath Bilbao","FT":"1-1","HT":"1-0"},
{"Date":"1999-12-12","Team 1":"Espanol","Team 2":"Valladolid","FT":"1-1","HT":"1-0"},
{"Date":"1999-12-12","Team 1":"Mallorca","Team 2":"Oviedo","FT":"1-1","HT":"0-0"},
{"Date":"1999-12-12","Team 1":"Santander","Team 2":"Real Madrid","FT":"1-1","HT":"0-1"},
{"Date":"1999-12-12","Team 1":"Sociedad","Team 2":"La Coruna","FT":"0-1","HT":"0-1"},
{"Date":"1999-12-12","Team 1":"Vallecano","Team 2":"Malaga","FT":"4-1","HT":"2-1"},
{"Date":"1999-12-12","Team 1":"Zaragoza","Team 2":"Numancia","FT":"3-3","HT":"1-1"},
{"Date":"1999-12-18","Team 1":"La Coruna","Team 2":"Celta","FT":"1-0","HT":"0-0"},
{"Date":"1999-12-18","Team 1":"Real Madrid","Team 2":"Espanol","FT":"2-1","HT":"1-1"},
{"Date":"1999-12-18","Team 1":"Valladolid","Team 2":"Alaves","FT":"1-1","HT":"0-1"},
{"Date":"1999-12-19","Team 1":"Ath Bilbao","Team 2":"Zaragoza","FT":"2-2","HT":"2-2"},
{"Date":"1999-12-19","Team 1":"Barcelona","Team 2":"Ath Madrid","FT":"2-1","HT":"1-1"},
{"Date":"1999-12-19","Team 1":"Betis","Team 2":"Mallorca","FT":"1-0","HT":"0-0"},
{"Date":"1999-12-19","Team 1":"Malaga","Team 2":"Sociedad","FT":"0-0","HT":"0-0"},
{"Date":"1999-12-19","Team 1":"Numancia","Team 2":"Santander","FT":"2-1","HT":"1-0"},
{"Date":"1999-12-19","Team 1":"Oviedo","Team 2":"Sevilla","FT":"4-2","HT":"1-1"},
{"Date":"1999-12-19","Team 1":"Valencia","Team 2":"Vallecano","FT":"3-1","HT":"1-0"},
{"Date":"1999-12-21","Team 1":"Alaves","Team 2":"Real Madrid","FT":"1-3","HT":"0-1"},
{"Date":"1999-12-22","Team 1":"Ath Madrid","Team 2":"Oviedo","FT":"5-0","HT":"3-0"},
{"Date":"1999-12-22","Team 1":"Betis","Team 2":"Valladolid","FT":"0-1","HT":"0-0"},
{"Date":"1999-12-22","Team 1":"Celta","Team 2":"Malaga","FT":"2-4","HT":"1-1"},
{"Date":"1999-12-22","Team 1":"Espanol","Team 2":"Numancia","FT":"3-1","HT":"0-1"},
{"Date":"1999-12-22","Team 1":"Mallorca","Team 2":"Sevilla","FT":"3-1","HT":"0-0"},
{"Date":"1999-12-22","Team 1":"Santander","Team 2":"Ath Bilbao","FT":"2-2","HT":"1-1"},
{"Date":"1999-12-22","Team 1":"Sociedad","Team 2":"Valencia","FT":"0-0","HT":"0-0"},
{"Date":"1999-12-22","Team 1":"Vallecano","Team 2":"Barcelona","FT":"1-1","HT":"1-0"},
{"Date":"1999-12-22","Team 1":"Zaragoza","Team 2":"La Coruna","FT":"2-1","HT":"1-0"},
{"Date":"2000-01-04","Team 1":"Valencia","Team 2":"Celta","FT":"1-1","HT":"1-0"},
{"Date":"2000-01-05","Team 1":"Ath Bilbao","Team 2":"Espanol","FT":"2-1","HT":"1-1"},
{"Date":"2000-01-05","Team 1":"Barcelona","Team 2":"Sociedad","FT":"3-1","HT":"2-0"},
{"Date":"2000-01-05","Team 1":"La Coruna","Team 2":"Santander","FT":"0-3","HT":"0-1"},
{"Date":"2000-01-05","Team 1":"Malaga","Team 2":"Zaragoza","FT":"0-0","HT":"0-0"},
{"Date":"2000-01-05","Team 1":"Mallorca","Team 2":"Valladolid","FT":"0-0","HT":"0-0"},
{"Date":"2000-01-05","Team 1":"Numancia","Team 2":"Alaves","FT":"0-0","HT":"0-0"},
{"Date":"2000-01-05","Team 1":"Oviedo","Team 2":"Vallecano","FT":"2-0","HT":"1-0"},
{"Date":"2000-01-05","Team 1":"Sevilla","Team 2":"Ath Madrid","FT":"2-1","HT":"2-0"},
{"Date":"2000-01-08","Team 1":"Espanol","Team 2":"La Coruna","FT":"0-0","HT":"0-0"},
{"Date":"2000-01-09","Team 1":"Alaves","Team 2":"Ath Bilbao","FT":"1-2","HT":"1-1"},
{"Date":"2000-01-09","Team 1":"Ath Madrid","Team 2":"Mallorca","FT":"1-0","HT":"0-0"},
{"Date":"2000-01-09","Team 1":"Betis","Team 2":"Numancia","FT":"1-2","HT":"1-0"},
{"Date":"2000-01-09","Team 1":"Celta","Team 2":"Barcelona","FT":"0-2","HT":"0-1"},
{"Date":"2000-01-09","Team 1":"Santander","Team 2":"Malaga","FT":"2-3","HT":"1-1"},
{"Date":"2000-01-09","Team 1":"Sociedad","Team 2":"Oviedo","FT":"0-0","HT":"0-0"},
{"Date":"2000-01-09","Team 1":"Vallecano","Team 2":"Sevilla","FT":"2-0","HT":"1-0"},
{"Date":"2000-01-09","Team 1":"Zaragoza","Team 2":"Valencia","FT":"4-2","HT":"2-1"},
{"Date":"2000-01-15","Team 1":"Vallecano","Team 2":"Ath Madrid","FT":"1-1","HT":"1-1"},
{"Date":"2000-01-16","Team 1":"Alaves","Team 2":"La Coruna","FT":"2-1","HT":"1-0"},
{"Date":"2000-01-16","Team 1":"Betis","Team 2":"Ath Bilbao","FT":"2-1","HT":"1-0"},
{"Date":"2000-01-16","Team 1":"Celta","Team 2":"Oviedo","FT":"5-3","HT":"4-2"},
{"Date":"2000-01-16","Team 1":"Espanol","Team 2":"Malaga","FT":"0-2","HT":"0-0"},
{"Date":"2000-01-16","Team 1":"Santander","Team 2":"Valencia","FT":"1-1","HT":"0-1"},
{"Date":"2000-01-16","Team 1":"Sociedad","Team 2":"Sevilla","FT":"1-1","HT":"0-1"},
{"Date":"2000-01-16","Team 1":"Valladolid","Team 2":"Numancia","FT":"2-0","HT":"0-0"},
{"Date":"2000-01-16","Team 1":"Zaragoza","Team 2":"Barcelona","FT":"0-0","HT":"0-0"},
{"Date":"2000-01-17","Team 1":"Real Madrid","Team 2":"Mallorca","FT":"2-1","HT":"0-1"},
{"Date":"2000-01-22","Team 1":"La Coruna","Team 2":"Betis","FT":"2-0","HT":"1-0"},
{"Date":"2000-01-23","Team 1":"Ath Bilbao","Team 2":"Valladolid","FT":"1-0","HT":"1-0"},
{"Date":"2000-01-23","Team 1":"Ath Madrid","Team 2":"Sociedad","FT":"1-1","HT":"1-0"},
{"Date":"2000-01-23","Team 1":"Barcelona","Team 2":"Santander","FT":"1-0","HT":"1-0"},
{"Date":"2000-01-23","Team 1":"Malaga","Team 2":"Alaves","FT":"0-1","HT":"0-1"},
{"Date":"2000-01-23","Team 1":"Mallorca","Team 2":"Vallecano","FT":"2-1","HT":"1-0"},
{"Date":"2000-01-23","Team 1":"Numancia","Team 2":"Real Madrid","FT":"0-0","HT":"0-0"},
{"Date":"2000-01-23","Team 1":"Oviedo","Team 2":"Zaragoza","FT":"1-0","HT":"0-0"},
{"Date":"2000-01-23","Team 1":"Sevilla","Team 2":"Celta","FT":"0-1","HT":"0-0"},
{"Date":"2000-01-23","Team 1":"Valencia","Team 2":"Espanol","FT":"1-2","HT":"1-1"},
{"Date":"2000-01-26","Team 1":"Real Madrid","Team 2":"Betis","FT":"2-1","HT":"0-0"},
{"Date":"2000-01-29","Team 1":"Celta","Team 2":"Ath Madrid","FT":"0-1","HT":"0-1"},
{"Date":"2000-01-29","Team 1":"Espanol","Team 2":"Barcelona","FT":"1-1","HT":"1-1"},
{"Date":"2000-01-30","Team 1":"Alaves","Team 2":"Valencia","FT":"0-1","HT":"0-0"},
{"Date":"2000-01-30","Team 1":"Betis","Team 2":"Malaga","FT":"0-0","HT":"0-0"},
{"Date":"2000-01-30","Team 1":"Numancia","Team 2":"Mallorca","FT":"3-1","HT":"3-1"},
{"Date":"2000-01-30","Team 1":"Real Madrid","Team 2":"Ath Bilbao","FT":"3-1","HT":"1-1"},
{"Date":"2000-01-30","Team 1":"Santander","Team 2":"Oviedo","FT":"3-1","HT":"2-0"},
{"Date":"2000-01-30","Team 1":"Sociedad","Team 2":"Vallecano","FT":"2-1","HT":"2-0"},
{"Date":"2000-01-30","Team 1":"Valladolid","Team 2":"La Coruna","FT":"4-1","HT":"1-0"},
{"Date":"2000-01-30","Team 1":"Zaragoza","Team 2":"Sevilla","FT":"2-1","HT":"1-0"},
{"Date":"2000-02-05","Team 1":"Valencia","Team 2":"Betis","FT":"3-1","HT":"1-0"},
{"Date":"2000-02-06","Team 1":"Ath Bilbao","Team 2":"Numancia","FT":"2-1","HT":"1-1"},
{"Date":"2000-02-06","Team 1":"Ath Madrid","Team 2":"Zaragoza","FT":"2-2","HT":"1-0"},
{"Date":"2000-02-06","Team 1":"Barcelona","Team 2":"Alaves","FT":"0-1","HT":"0-1"},
{"Date":"2000-02-06","Team 1":"La Coruna","Team 2":"Real Madrid","FT":"5-2","HT":"2-1"},
{"Date":"2000-02-06","Team 1":"Malaga","Team 2":"Valladolid","FT":"0-0","HT":"0-0"},
{"Date":"2000-02-06","Team 1":"Mallorca","Team 2":"Sociedad","FT":"2-1","HT":"1-0"},
{"Date":"2000-02-06","Team 1":"Oviedo","Team 2":"Espanol","FT":"1-0","HT":"0-0"},
{"Date":"2000-02-06","Team 1":"Sevilla","Team 2":"Santander","FT":"1-0","HT":"0-0"},
{"Date":"2000-02-06","Team 1":"Vallecano","Team 2":"Celta","FT":"1-0","HT":"1-0"},
{"Date":"2000-02-12","Team 1":"Ath Bilbao","Team 2":"Mallorca","FT":"1-1","HT":"0-1"},
{"Date":"2000-02-12","Team 1":"Real Madrid","Team 2":"Malaga","FT":"1-0","HT":"0-0"},
{"Date":"2000-02-12","Team 1":"Valladolid","Team 2":"Valencia","FT":"0-0","HT":"0-0"},
{"Date":"2000-02-13","Team 1":"Alaves","Team 2":"Oviedo","FT":"1-0","HT":"1-0"},
{"Date":"2000-02-13","Team 1":"Betis","Team 2":"Barcelona","FT":"2-1","HT":"1-0"},
{"Date":"2000-02-13","Team 1":"Celta","Team 2":"Sociedad","FT":"4-1","HT":"0-1"},
{"Date":"2000-02-13","Team 1":"Espanol","Team 2":"Sevilla","FT":"2-2","HT":"1-1"},
{"Date":"2000-02-13","Team 1":"Numancia","Team 2":"La Coruna","FT":"1-0","HT":"0-0"},
{"Date":"2000-02-13","Team 1":"Santander","Team 2":"Ath Madrid","FT":"2-1","HT":"1-1"},
{"Date":"2000-02-13","Team 1":"Zaragoza","Team 2":"Vallecano","FT":"1-1","HT":"1-0"},
{"Date":"2000-02-15","Team 1":"Valladolid","Team 2":"Real Madrid","FT":"0-1","HT":"0-0"},
{"Date":"2000-02-19","Team 1":"La Coruna","Team 2":"Ath Bilbao","FT":"2-0","HT":"1-0"},
{"Date":"2000-02-20","Team 1":"Ath Madrid","Team 2":"Espanol","FT":"1-1","HT":"1-0"},
{"Date":"2000-02-20","Team 1":"Barcelona","Team 2":"Valladolid","FT":"4-0","HT":"2-0"},
{"Date":"2000-02-20","Team 1":"Malaga","Team 2":"Numancia","FT":"3-1","HT":"1-1"},
{"Date":"2000-02-20","Team 1":"Mallorca","Team 2":"Celta","FT":"1-0","HT":"0-0"},
{"Date":"2000-02-20","Team 1":"Oviedo","Team 2":"Betis","FT":"1-1","HT":"0-1"},
{"Date":"2000-02-20","Team 1":"Sevilla","Team 2":"Alaves","FT":"2-2","HT":"1-1"},
{"Date":"2000-02-20","Team 1":"Sociedad","Team 2":"Zaragoza","FT":"2-1","HT":"1-0"},
{"Date":"2000-02-20","Team 1":"Valencia","Team 2":"Real Madrid","FT":"1-1","HT":"1-0"},
{"Date":"2000-02-20","Team 1":"Vallecano","Team 2":"Santander","FT":"1-2","HT":"1-1"},
{"Date":"2000-02-26","Team 1":"Numancia","Team 2":"Valencia","FT":"1-2","HT":"0-1"},
{"Date":"2000-02-26","Team 1":"Real Madrid","Team 2":"Barcelona","FT":"3-0","HT":"2-0"},
{"Date":"2000-02-27","Team 1":"Alaves","Team 2":"Ath Madrid","FT":"2-0","HT":"0-0"},
{"Date":"2000-02-27","Team 1":"Ath Bilbao","Team 2":"Malaga","FT":"2-2","HT":"1-2"},
{"Date":"2000-02-27","Team 1":"Betis","Team 2":"Sevilla","FT":"1-1","HT":"1-1"},
{"Date":"2000-02-27","Team 1":"Espanol","Team 2":"Vallecano","FT":"5-1","HT":"2-1"},
{"Date":"2000-02-27","Team 1":"La Coruna","Team 2":"Mallorca","FT":"2-1","HT":"1-0"},
{"Date":"2000-02-27","Team 1":"Santander","Team 2":"Sociedad","FT":"0-0","HT":"0-0"},
{"Date":"2000-02-27","Team 1":"Valladolid","Team 2":"Oviedo","FT":"2-1","HT":"1-0"},
{"Date":"2000-02-27","Team 1":"Zaragoza","Team 2":"Celta","FT":"2-1","HT":"0-1"},
{"Date":"2000-03-04","Team 1":"Barcelona","Team 2":"Numancia","FT":"4-0","HT":"1-0"},
{"Date":"2000-03-04","Team 1":"Oviedo","Team 2":"Real Madrid","FT":"1-1","HT":"0-0"},
{"Date":"2000-03-04","Team 1":"Valencia","Team 2":"Ath Bilbao","FT":"2-0","HT":"0-0"},
{"Date":"2000-03-05","Team 1":"Ath Madrid","Team 2":"Betis","FT":"0-0","HT":"0-0"},
{"Date":"2000-03-05","Team 1":"Celta","Team 2":"Santander","FT":"2-0","HT":"1-0"},
{"Date":"2000-03-05","Team 1":"Malaga","Team 2":"La Coruna","FT":"1-0","HT":"1-0"},
{"Date":"2000-03-05","Team 1":"Mallorca","Team 2":"Zaragoza","FT":"1-1","HT":"1-0"},
{"Date":"2000-03-05","Team 1":"Sevilla","Team 2":"Valladolid","FT":"0-1","HT":"0-0"},
{"Date":"2000-03-05","Team 1":"Sociedad","Team 2":"Espanol","FT":"1-0","HT":"1-0"},
{"Date":"2000-03-05","Team 1":"Vallecano","Team 2":"Alaves","FT":"0-1","HT":"0-0"},
{"Date":"2000-03-11","Team 1":"Ath Bilbao","Team 2":"Barcelona","FT":"0-4","HT":"0-2"},
{"Date":"2000-03-11","Team 1":"Betis","Team 2":"Vallecano","FT":"1-1","HT":"1-0"},
{"Date":"2000-03-11","Team 1":"Real Madrid","Team 2":"Sevilla","FT":"3-1","HT":"3-0"},
{"Date":"2000-03-12","Team 1":"Alaves","Team 2":"Sociedad","FT":"2-1","HT":"0-1"},
{"Date":"2000-03-12","Team 1":"Espanol","Team 2":"Celta","FT":"3-0","HT":"0-0"},
{"Date":"2000-03-12","Team 1":"La Coruna","Team 2":"Valencia","FT":"2-0","HT":"1-0"},
{"Date":"2000-03-12","Team 1":"Malaga","Team 2":"Mallorca","FT":"0-0","HT":"0-0"},
{"Date":"2000-03-12","Team 1":"Numancia","Team 2":"Oviedo","FT":"1-1","HT":"0-1"},
{"Date":"2000-03-12","Team 1":"Santander","Team 2":"Zaragoza","FT":"1-2","HT":"1-0"},
{"Date":"2000-03-12","Team 1":"Valladolid","Team 2":"Ath Madrid","FT":"1-0","HT":"1-0"},
{"Date":"2000-03-18","Team 1":"Ath Madrid","Team 2":"Real Madrid","FT":"1-1","HT":"0-1"},
{"Date":"2000-03-18","Team 1":"Barcelona","Team 2":"La Coruna","FT":"2-1","HT":"2-0"},
{"Date":"2000-03-18","Team 1":"Valencia","Team 2":"Malaga","FT":"2-2","HT":"0-0"},
{"Date":"2000-03-19","Team 1":"Celta","Team 2":"Alaves","FT":"1-1","HT":"0-0"},
{"Date":"2000-03-19","Team 1":"Mallorca","Team 2":"Santander","FT":"1-2","HT":"0-1"},
{"Date":"2000-03-19","Team 1":"Oviedo","Team 2":"Ath Bilbao","FT":"1-0","HT":"1-0"},
{"Date":"2000-03-19","Team 1":"Sevilla","Team 2":"Numancia","FT":"4-0","HT":"1-0"},
{"Date":"2000-03-19","Team 1":"Sociedad","Team 2":"Betis","FT":"1-0","HT":"0-0"},
{"Date":"2000-03-19","Team 1":"Vallecano","Team 2":"Valladolid","FT":"4-1","HT":"1-0"},
{"Date":"2000-03-19","Team 1":"Zaragoza","Team 2":"Espanol","FT":"1-1","HT":"1-0"},
{"Date":"2000-03-25","Team 1":"Alaves","Team 2":"Zaragoza","FT":"0-2","HT":"0-0"},
{"Date":"2000-03-25","Team 1":"Ath Bilbao","Team 2":"Sevilla","FT":"1-1","HT":"1-0"},
{"Date":"2000-03-25","Team 1":"Espanol","Team 2":"Santander","FT":"1-0","HT":"0-0"},
{"Date":"2000-03-25","Team 1":"Malaga","Team 2":"Barcelona","FT":"1-2","HT":"1-0"},
{"Date":"2000-03-25","Team 1":"Numancia","Team 2":"Ath Madrid","FT":"3-0","HT":"1-0"},
{"Date":"2000-03-25","Team 1":"Real Madrid","Team 2":"Vallecano","FT":"0-0","HT":"0-0"},
{"Date":"2000-03-25","Team 1":"Valencia","Team 2":"Mallorca","FT":"1-0","HT":"0-0"},
{"Date":"2000-03-25","Team 1":"Valladolid","Team 2":"Sociedad","FT":"2-1","HT":"0-1"},
{"Date":"2000-03-26","Team 1":"Betis","Team 2":"Celta","FT":"0-0","HT":"0-0"},
{"Date":"2000-03-26","Team 1":"La Coruna","Team 2":"Oviedo","FT":"3-1","HT":"2-0"},
{"Date":"2000-04-01","Team 1":"Sociedad","Team 2":"Real Madrid","FT":"1-1","HT":"0-1"},
{"Date":"2000-04-02","Team 1":"Ath Madrid","Team 2":"Ath Bilbao","FT":"1-2","HT":"1-1"},
{"Date":"2000-04-02","Team 1":"Barcelona","Team 2":"Valencia","FT":"3-0","HT":"0-0"},
{"Date":"2000-04-02","Team 1":"Celta","Team 2":"Valladolid","FT":"1-1","HT":"1-0"},
{"Date":"2000-04-02","Team 1":"Mallorca","Team 2":"Espanol","FT":"1-3","HT":"1-1"},
{"Date":"2000-04-02","Team 1":"Oviedo","Team 2":"Malaga","FT":"2-2","HT":"2-1"},
{"Date":"2000-04-02","Team 1":"Santander","Team 2":"Alaves","FT":"0-0","HT":"0-0"},
{"Date":"2000-04-02","Team 1":"Sevilla","Team 2":"La Coruna","FT":"1-3","HT":"1-2"},
{"Date":"2000-04-02","Team 1":"Vallecano","Team 2":"Numancia","FT":"0-0","HT":"0-0"},
{"Date":"2000-04-02","Team 1":"Zaragoza","Team 2":"Betis","FT":"1-0","HT":"0-0"},
{"Date":"2000-04-08","Team 1":"La Coruna","Team 2":"Ath Madrid","FT":"4-1","HT":"3-0"},
{"Date":"2000-04-09","Team 1":"Alaves","Team 2":"Espanol","FT":"0-0","HT":"0-0"},
{"Date":"2000-04-09","Team 1":"Ath Bilbao","Team 2":"Vallecano","FT":"1-2","HT":"0-2"},
{"Date":"2000-04-09","Team 1":"Barcelona","Team 2":"Mallorca","FT":"0-3","HT":"0-1"},
{"Date":"2000-04-09","Team 1":"Betis","Team 2":"Santander","FT":"2-2","HT":"1-0"},
{"Date":"2000-04-09","Team 1":"Malaga","Team 2":"Sevilla","FT":"3-0","HT":"0-0"},
{"Date":"2000-04-09","Team 1":"Numancia","Team 2":"Sociedad","FT":"1-2","HT":"0-0"},
{"Date":"2000-04-09","Team 1":"Real Madrid","Team 2":"Celta","FT":"1-0","HT":"0-0"},
{"Date":"2000-04-09","Team 1":"Valencia","Team 2":"Oviedo","FT":"6-2","HT":"2-0"},
{"Date":"2000-04-09","Team 1":"Valladolid","Team 2":"Zaragoza","FT":"1-1","HT":"0-0"},
{"Date":"2000-04-15","Team 1":"Oviedo","Team 2":"Barcelona","FT":"3-0","HT":"1-0"},
{"Date":"2000-04-15","Team 1":"Sevilla","Team 2":"Valencia","FT":"1-2","HT":"0-0"},
{"Date":"2000-04-15","Team 1":"Zaragoza","Team 2":"Real Madrid","FT":"0-1","HT":"0-0"},
{"Date":"2000-04-16","Team 1":"Ath Madrid","Team 2":"Malaga","FT":"2-2","HT":"1-1"},
{"Date":"2000-04-16","Team 1":"Celta","Team 2":"Numancia","FT":"0-0","HT":"0-0"},
{"Date":"2000-04-16","Team 1":"Espanol","Team 2":"Betis","FT":"3-0","HT":"0-0"},
{"Date":"2000-04-16","Team 1":"Mallorca","Team 2":"Alaves","FT":"2-0","HT":"1-0"},
{"Date":"2000-04-16","Team 1":"Santander","Team 2":"Valladolid","FT":"1-1","HT":"1-0"},
{"Date":"2000-04-16","Team 1":"Sociedad","Team 2":"Ath Bilbao","FT":"4-1","HT":"1-1"},
{"Date":"2000-04-16","Team 1":"Vallecano","Team 2":"La Coruna","FT":"2-0","HT":"1-0"},
{"Date":"2000-04-22","Team 1":"Ath Bilbao","Team 2":"Celta","FT":"1-0","HT":"0-0"},
{"Date":"2000-04-22","Team 1":"Barcelona","Team 2":"Sevilla","FT":"2-0","HT":"1-0"},
{"Date":"2000-04-22","Team 1":"Malaga","Team 2":"Vallecano","FT":"2-0","HT":"1-0"},
{"Date":"2000-04-22","Team 1":"Numancia","Team 2":"Zaragoza","FT":"1-2","HT":"1-2"},
{"Date":"2000-04-22","Team 1":"Real Madrid","Team 2":"Santander","FT":"2-4","HT":"1-2"},
{"Date":"2000-04-22","Team 1":"Valencia","Team 2":"Ath Madrid","FT":"2-0","HT":"1-0"},
{"Date":"2000-04-22","Team 1":"Valladolid","Team 2":"Espanol","FT":"1-0","HT":"0-0"},
{"Date":"2000-04-23","Team 1":"Betis","Team 2":"Alaves","FT":"0-1","HT":"0-0"},
{"Date":"2000-04-23","Team 1":"La Coruna","Team 2":"Sociedad","FT":"2-0","HT":"2-0"},
{"Date":"2000-04-23","Team 1":"Oviedo","Team 2":"Mallorca","FT":"0-0","HT":"0-0"},
{"Date":"2000-04-29","Team 1":"Ath Madrid","Team 2":"Barcelona","FT":"0-3","HT":"0-1"},
{"Date":"2000-04-29","Team 1":"Espanol","Team 2":"Real Madrid","FT":"0-2","HT":"0-0"},
{"Date":"2000-04-29","Team 1":"Vallecano","Team 2":"Valencia","FT":"1-3","HT":"0-2"},
{"Date":"2000-04-30","Team 1":"Alaves","Team 2":"Valladolid","FT":"1-0","HT":"1-0"},
{"Date":"2000-04-30","Team 1":"Celta","Team 2":"La Coruna","FT":"2-1","HT":"1-0"},
{"Date":"2000-04-30","Team 1":"Mallorca","Team 2":"Betis","FT":"4-0","HT":"3-0"},
{"Date":"2000-04-30","Team 1":"Santander","Team 2":"Numancia","FT":"1-1","HT":"1-0"},
{"Date":"2000-04-30","Team 1":"Sevilla","Team 2":"Oviedo","FT":"2-3","HT":"0-1"},
{"Date":"2000-04-30","Team 1":"Sociedad","Team 2":"Malaga","FT":"2-2","HT":"1-0"},
{"Date":"2000-04-30","Team 1":"Zaragoza","Team 2":"Ath Bilbao","FT":"0-0","HT":"0-0"},
{"Date":"2000-05-06","Team 1":"Barcelona","Team 2":"Vallecano","FT":"0-2","HT":"0-1"},
{"Date":"2000-05-06","Team 1":"Numancia","Team 2":"Espanol","FT":"2-0","HT":"1-0"},
{"Date":"2000-05-06","Team 1":"Real Madrid","Team 2":"Alaves","FT":"0-1","HT":"0-0"},
{"Date":"2000-05-06","Team 1":"Valencia","Team 2":"Sociedad","FT":"4-0","HT":"1-0"},
{"Date":"2000-05-07","Team 1":"Ath Bilbao","Team 2":"Santander","FT":"2-2","HT":"2-2"},
{"Date":"2000-05-07","Team 1":"La Coruna","Team 2":"Zaragoza","FT":"2-2","HT":"0-0"},
{"Date":"2000-05-07","Team 1":"Malaga","Team 2":"Celta","FT":"0-1","HT":"0-1"},
{"Date":"2000-05-07","Team 1":"Oviedo","Team 2":"Ath Madrid","FT":"2-2","HT":"1-0"},
{"Date":"2000-05-07","Team 1":"Sevilla","Team 2":"Mallorca","FT":"0-4","HT":"0-1"},
{"Date":"2000-05-07","Team 1":"Valladolid","Team 2":"Betis","FT":"0-3","HT":"0-1"},
{"Date":"2000-05-13","Team 1":"Ath Madrid","Team 2":"Sevilla","FT":"1-1","HT":"1-1"},
{"Date":"2000-05-14","Team 1":"Alaves","Team 2":"Numancia","FT":"2-2","HT":"0-1"},
{"Date":"2000-05-14","Team 1":"Betis","Team 2":"Real Madrid","FT":"0-2","HT":"0-1"},
{"Date":"2000-05-14","Team 1":"Celta","Team 2":"Valencia","FT":"0-0","HT":"0-0"},
{"Date":"2000-05-14","Team 1":"Espanol","Team 2":"Ath Bilbao","FT":"0-0","HT":"0-0"},
{"Date":"2000-05-14","Team 1":"Santander","Team 2":"La Coruna","FT":"0-0","HT":"0-0"},
{"Date":"2000-05-14","Team 1":"Sociedad","Team 2":"Barcelona","FT":"0-0","HT":"0-0"},
{"Date":"2000-05-14","Team 1":"Valladolid","Team 2":"Mallorca","FT":"2-1","HT":"0-0"},
{"Date":"2000-05-14","Team 1":"Vallecano","Team 2":"Oviedo","FT":"1-2","HT":"1-1"},
{"Date":"2000-05-14","Team 1":"Zaragoza","Team 2":"Malaga","FT":"3-2","HT":"1-1"},
{"Date":"2000-05-19","Team 1":"Ath Bilbao","Team 2":"Alaves","FT":"2-1","HT":"1-1"},
{"Date":"2000-05-19","Team 1":"Barcelona","Team 2":"Celta","FT":"2-2","HT":"0-2"},
{"Date":"2000-05-19","Team 1":"La Coruna","Team 2":"Espanol","FT":"2-0","HT":"2-0"},
{"Date":"2000-05-19","Team 1":"Mallorca","Team 2":"Ath Madrid","FT":"1-2","HT":"1-2"},
{"Date":"2000-05-19","Team 1":"Real Madrid","Team 2":"Valladolid","FT":"0-1","HT":"0-1"},
{"Date":"2000-05-19","Team 1":"Sevilla","Team 2":"Vallecano","FT":"2-3","HT":"1-2"},
{"Date":"2000-05-19","Team 1":"Valencia","Team 2":"Zaragoza","FT":"2-1","HT":"0-1"},
{"Date":"2000-05-20","Team 1":"Malaga","Team 2":"Santander","FT":"0-0","HT":"0-0"},
{"Date":"2000-05-20","Team 1":"Numancia","Team 2":"Betis","FT":"1-2","HT":"0-0"},
{"Date":"2000-05-20","Team 1":"Oviedo","Team 2":"Sociedad","FT":"0-1","HT":"0-0"}
]