[
{"Team":"La_Coruna","Played":42,"Won":29,"Lose":4,"Draw":9,"FT:HT":"76:45","Points":91},
{"Team":"Celta","Played":42,"Won":26,"Lose":7,"Draw":9,"FT:HT":"83:37","Points":85},
{"Team":"Valladolid","Played":42,"Won":23,"Lose":13,"Draw":6,"FT:HT":"69:37","Points":82},
{"Team":"Alcorcon","Played":42,"Won":21,"Lose":10,"Draw":11,"FT:HT":"58:42","Points":73},
{"Team":"Hercules","Played":42,"Won":22,"Lose":6,"Draw":14,"FT:HT":"62:43","Points":72},
{"Team":"Cordoba","Played":42,"Won":20,"Lose":11,"Draw":11,"FT:HT":"52:43","Points":71},
{"Team":"Almeria","Played":42,"Won":18,"Lose":16,"Draw":8,"FT:HT":"63:43","Points":70},
{"Team":"Barcelona_B","Played":42,"Won":16,"Lose":11,"Draw":15,"FT:HT":"63:53","Points":59},
{"Team":"Las_Palmas","Played":42,"Won":16,"Lose":10,"Draw":16,"FT:HT":"58:59","Points":58},
{"Team":"Numancia","Played":42,"Won":15,"Lose":12,"Draw":15,"FT:HT":"54:52","Points":57},
{"Team":"Elche","Played":42,"Won":17,"Lose":6,"Draw":19,"FT:HT":"56:58","Points":57},
{"Team":"Villarreal_B","Played":42,"Won":14,"Lose":10,"Draw":18,"FT:HT":"54:64","Points":52},
{"Team":"Huesca","Played":42,"Won":14,"Lose":9,"Draw":19,"FT:HT":"49:63","Points":51},
{"Team":"Xerez","Played":42,"Won":13,"Lose":11,"Draw":18,"FT:HT":"50:66","Points":50},
{"Team":"Girona","Played":42,"Won":12,"Lose":13,"Draw":17,"FT:HT":"58:61","Points":49},
{"Team":"Guadalajara","Played":42,"Won":14,"Lose":7,"Draw":21,"FT:HT":"50:75","Points":49},
{"Team":"Recreativo","Played":42,"Won":12,"Lose":11,"Draw":19,"FT:HT":"49:52","Points":47},
{"Team":"Murcia","Played":42,"Won":13,"Lose":8,"Draw":21,"FT:HT":"49:67","Points":47},
{"Team":"Sabadell","Played":42,"Won":11,"Lose":13,"Draw":18,"FT:HT":"45:64","Points":46},
{"Team":"Cartagena","Played":42,"Won":9,"Lose":13,"Draw":20,"FT:HT":"37:58","Points":40},
{"Team":"Alcoyano","Played":42,"Won":9,"Lose":10,"Draw":23,"FT:HT":"46:78","Points":37},
{"Team":"Gimnastic","Played":42,"Won":6,"Lose":13,"Draw":23,"FT:HT":"37:58","Points":31}
]