[
{"Team":"Real_Madrid","Played":38,"Won":22,"Lose":12,"Draw":4,"FT:HT":"86:42","Points":78},
{"Team":"Sociedad","Played":38,"Won":22,"Lose":10,"Draw":6,"FT:HT":"71:45","Points":76},
{"Team":"La_Coruna","Played":38,"Won":22,"Lose":6,"Draw":10,"FT:HT":"67:47","Points":72},
{"Team":"Celta","Played":38,"Won":17,"Lose":10,"Draw":11,"FT:HT":"45:36","Points":61},
{"Team":"Valencia","Played":38,"Won":17,"Lose":9,"Draw":12,"FT:HT":"56:35","Points":60},
{"Team":"Barcelona","Played":38,"Won":15,"Lose":11,"Draw":12,"FT:HT":"63:47","Points":56},
{"Team":"Ath_Bilbao","Played":38,"Won":15,"Lose":10,"Draw":13,"FT:HT":"63:61","Points":55},
{"Team":"Betis","Played":38,"Won":14,"Lose":12,"Draw":12,"FT:HT":"56:53","Points":54},
{"Team":"Mallorca","Played":38,"Won":14,"Lose":10,"Draw":14,"FT:HT":"49:56","Points":52},
{"Team":"Sevilla","Played":38,"Won":13,"Lose":11,"Draw":14,"FT:HT":"38:39","Points":50},
{"Team":"Ath_Madrid","Played":38,"Won":12,"Lose":11,"Draw":15,"FT:HT":"51:56","Points":47},
{"Team":"Osasuna","Played":38,"Won":12,"Lose":11,"Draw":15,"FT:HT":"40:48","Points":47},
{"Team":"Valladolid","Played":38,"Won":12,"Lose":10,"Draw":16,"FT:HT":"37:40","Points":46},
{"Team":"Malaga","Played":38,"Won":11,"Lose":13,"Draw":14,"FT:HT":"44:49","Points":46},
{"Team":"Villarreal","Played":38,"Won":11,"Lose":12,"Draw":15,"FT:HT":"44:53","Points":45},
{"Team":"Santander","Played":38,"Won":13,"Lose":5,"Draw":20,"FT:HT":"54:64","Points":44},
{"Team":"Espanol","Played":38,"Won":10,"Lose":13,"Draw":15,"FT:HT":"48:54","Points":43},
{"Team":"Recreativo","Played":38,"Won":8,"Lose":12,"Draw":18,"FT:HT":"35:61","Points":36},
{"Team":"Alaves","Played":38,"Won":8,"Lose":11,"Draw":19,"FT:HT":"38:68","Points":35},
{"Team":"Vallecano","Played":38,"Won":7,"Lose":11,"Draw":20,"FT:HT":"31:62","Points":32}
]